azure/cli/command_modules/sf/__init__.py
azure/cli/command_modules/sf/_factory.py
azure/cli/command_modules/sf/_help.py
azure/cli/command_modules/sf/_params.py
azure/cli/command_modules/sf/cluster_auth.py
azure/cli/command_modules/sf/commands.py
azure/cli/command_modules/sf/config.py
azure/cli/command_modules/sf/custom.py
azure_cli_sf-1.0.8.dist-info/DESCRIPTION.rst
azure_cli_sf-1.0.8.dist-info/METADATA
azure_cli_sf-1.0.8.dist-info/RECORD
azure_cli_sf-1.0.8.dist-info/WHEEL
azure_cli_sf-1.0.8.dist-info/metadata.json
azure_cli_sf-1.0.8.dist-info/top_level.txt
