Metadata-Version: 2.0
Name: azure-cli-sf
Version: 1.0.8
Summary: Microsoft Azure Service Fabric Client Command-Line Tools
Home-page: https://github.com/Azure/azure-cli
Author: Microsoft Corporation
Author-email: azpycli@microsoft.com
License: MIT
Platform: UNKNOWN
Classifier: Development Status :: 4 - Beta
Classifier: Intended Audience :: Developers
Classifier: Intended Audience :: System Administrators
Classifier: Programming Language :: Python
Classifier: Programming Language :: Python :: 2
Classifier: Programming Language :: Python :: 2.7
Classifier: Programming Language :: Python :: 3
Classifier: Programming Language :: Python :: 3.4
Classifier: Programming Language :: Python :: 3.5
Classifier: Programming Language :: Python :: 3.6
Classifier: License :: OSI Approved :: MIT License
Requires-Dist: adal (>=0.4.3)
Requires-Dist: azure-cli-command-modules-nspkg (>=2.0.0)
Requires-Dist: azure-cli-core
Requires-Dist: azure-servicefabric (==5.6.130)
Requires-Dist: mock (>=2.0.0)
